odoo/addons/push_rule_auto_create_group/README.rst
odoo/addons/push_rule_auto_create_group/__init__.py
odoo/addons/push_rule_auto_create_group/__manifest__.py
odoo/addons/push_rule_auto_create_group/i18n/push_rule_auto_create_group.pot
odoo/addons/push_rule_auto_create_group/models/__init__.py
odoo/addons/push_rule_auto_create_group/models/stock_location_path.py
odoo/addons/push_rule_auto_create_group/readme/CONFIGURE.rst
odoo/addons/push_rule_auto_create_group/readme/CONTRIBUTORS.rst
odoo/addons/push_rule_auto_create_group/readme/DESCRIPTION.rst
odoo/addons/push_rule_auto_create_group/readme/USAGE.rst
odoo/addons/push_rule_auto_create_group/static/description/icon.png
odoo/addons/push_rule_auto_create_group/static/description/index.html
odoo/addons/push_rule_auto_create_group/tests/__init__.py
odoo/addons/push_rule_auto_create_group/tests/test_auto_create.py
odoo/addons/push_rule_auto_create_group/views/stock_location_view.xml
odoo11_addon_push_rule_auto_create_group-11.0.1.0.1.dist-info/METADATA
odoo11_addon_push_rule_auto_create_group-11.0.1.0.1.dist-info/WHEEL
odoo11_addon_push_rule_auto_create_group-11.0.1.0.1.dist-info/top_level.txt
odoo11_addon_push_rule_auto_create_group-11.0.1.0.1.dist-info/RECORD
